{
    "43214ac5-feb7-4c5c-9846-69b4f7b1f2ce": {
        "ed5d5e05-674d-48da-a92f-44f1153bc5c1": {
            "TagComponent": {
                "Tag": "NewEntity"
            },
            "TransformComponent": {
                "Origin": [
                    0.0,
                    0.0
                ],
                "Rotation": 0.0,
                "Scale": [
                    1.0,
                    1.0
                ],
                "Translate": [
                    0.0,
                    0.0
                ]
            }
        }
    }
}
